setup.py
gb_gaussian_binomial_distribution/Binomialdistribution.py
gb_gaussian_binomial_distribution/Gaussiandistribution.py
gb_gaussian_binomial_distribution/Generaldistribution.py
gb_gaussian_binomial_distribution/__init__.py
gb_gaussian_binomial_distribution.egg-info/PKG-INFO
gb_gaussian_binomial_distribution.egg-info/SOURCES.txt
gb_gaussian_binomial_distribution.egg-info/dependency_links.txt
gb_gaussian_binomial_distribution.egg-info/not-zip-safe
gb_gaussian_binomial_distribution.egg-info/top_level.txt