Metadata-Version: 1.0
Name: gb-gaussian-binomial-distribution
Version: 0.1
Summary: Gaussian and Binomial distributions
Home-page: UNKNOWN
Author: Gianluca Bianco
Author-email: ciao@gianlucabianco.dev
License: UNKNOWN
Platform: UNKNOWN
